plerr/__init__.py
plerr/__main__.py
plerr/cli.py
plerr/errors/async/E1700.md
plerr/errors/async/E1701.md
plerr/errors/basic/C0102.md
plerr/errors/basic/C0103.md
plerr/errors/basic/C0112.md
plerr/errors/basic/C0114.md
plerr/errors/basic/C0115.md
plerr/errors/basic/C0116.md
plerr/errors/basic/C0121.md
plerr/errors/basic/C0122.md
plerr/errors/basic/C0123.md
plerr/errors/basic/E0100.md
plerr/errors/basic/E0101.md
plerr/errors/basic/E0102.md
plerr/errors/basic/E0103.md
plerr/errors/basic/E0104.md
plerr/errors/basic/E0105.md
plerr/errors/basic/E0106.md
plerr/errors/basic/E0107.md
plerr/errors/basic/E0108.md
plerr/errors/basic/E0110.md
plerr/errors/basic/E0111.md
plerr/errors/basic/E0112.md
plerr/errors/basic/E0113.md
plerr/errors/basic/E0114.md
plerr/errors/basic/E0115.md
plerr/errors/basic/E0116.md
plerr/errors/basic/E0117.md
plerr/errors/basic/E0118.md
plerr/errors/basic/E0119.md
plerr/errors/basic/R0123.md
plerr/errors/basic/R0124.md
plerr/errors/basic/W0101.md
plerr/errors/basic/W0102.md
plerr/errors/basic/W0104.md
plerr/errors/basic/W0105.md
plerr/errors/basic/W0106.md
plerr/errors/basic/W0107.md
plerr/errors/basic/W0108.md
plerr/errors/basic/W0109.md
plerr/errors/basic/W0111.md
plerr/errors/basic/W0120.md
plerr/errors/basic/W0122.md
plerr/errors/basic/W0123.md
plerr/errors/basic/W0124.md
plerr/errors/basic/W0125.md
plerr/errors/basic/W0126.md
plerr/errors/basic/W0127.md
plerr/errors/basic/W0128.md
plerr/errors/basic/W0143.md
plerr/errors/basic/W0150.md
plerr/errors/basic/W0199.md
plerr/errors/broad-try-clause/W0717.md
plerr/errors/classes/C0202.md
plerr/errors/classes/C0203.md
plerr/errors/classes/C0204.md
plerr/errors/classes/C0205.md
plerr/errors/classes/E0202.md
plerr/errors/classes/E0203.md
plerr/errors/classes/E0211.md
plerr/errors/classes/E0213.md
plerr/errors/classes/E0236.md
plerr/errors/classes/E0237.md
plerr/errors/classes/E0238.md
plerr/errors/classes/E0239.md
plerr/errors/classes/E0240.md
plerr/errors/classes/E0241.md
plerr/errors/classes/E0242.md
plerr-4.0.3.dist-info/LICENSE
plerr-4.0.3.dist-info/METADATA
plerr-4.0.3.dist-info/WHEEL
plerr-4.0.3.dist-info/entry_points.txt
plerr-4.0.3.dist-info/top_level.txt
plerr-4.0.3.dist-info/RECORD
