Metadata-Version: 2.1
Name: plerr
Version: 4.0.3
Summary: A list of pylint-errors with reasoning and examples of erroneous and correct code.
Home-page: https://github.com/sprytnyk/pylint-errors
Author: Vladyslav Krylasov
Author-email: vladyslav.krylasov@gmail.com
Keywords: pylint,errors,documentation
Classifier: Intended Audience :: Developers
Classifier: Natural Language :: English
Classifier: License :: OSI Approved :: MIT License
Classifier: Operating System :: OS Independent
Classifier: Programming Language :: Python
Classifier: Programming Language :: Python :: 3
Classifier: Programming Language :: Python :: 3.7
Classifier: Programming Language :: Python :: 3.8
Classifier: Programming Language :: Python :: 3.9
Classifier: Programming Language :: Python :: 3.10
Classifier: Programming Language :: Python :: 3.11
Classifier: Programming Language :: Python :: Implementation :: CPython
Classifier: Topic :: Software Development :: Documentation
Classifier: Topic :: Software Development :: Libraries :: Python Modules
Classifier: Topic :: Software Development :: Quality Assurance
Requires-Python: >=3.7
License-File: LICENSE
Requires-Dist: Pygments ==2.17.2
